RsCmwBase/RsCmwBase.py
RsCmwBase/__init__.py
RsCmwBase/enums.py
RsCmwBase/repcap.py
RsCmwBase/CustomFiles/__init__.py
RsCmwBase/CustomFiles/events.py
RsCmwBase/CustomFiles/reliability.py
RsCmwBase/CustomFiles/utilities.py
RsCmwBase/Implementations/FirmwareUpdate.py
RsCmwBase/Implementations/Get.py
RsCmwBase/Implementations/GlobalClearStatus.py
RsCmwBase/Implementations/GlobalWait.py
RsCmwBase/Implementations/GotoLocal.py
RsCmwBase/Implementations/MacroCreate.py
RsCmwBase/Implementations/Procedure.py
RsCmwBase/Implementations/RecallState.py
RsCmwBase/Implementations/SaveState.py
RsCmwBase/Implementations/TriggerInvoke.py
RsCmwBase/Implementations/Unit.py
RsCmwBase/Implementations/__init__.py
RsCmwBase/Implementations/Buffer/LineCount.py
RsCmwBase/Implementations/Buffer/__init__.py
RsCmwBase/Implementations/Calibration/Ipc.py
RsCmwBase/Implementations/Calibration/Ipcr.py
RsCmwBase/Implementations/Calibration/__init__.py
RsCmwBase/Implementations/Calibration/Latest/Specific.py
RsCmwBase/Implementations/Calibration/Latest/__init__.py
RsCmwBase/Implementations/Catalog/__init__.py
RsCmwBase/Implementations/Catalog/Correction/__init__.py
RsCmwBase/Implementations/Catalog/Correction/IfEqualizer/__init__.py
RsCmwBase/Implementations/Catalog/Correction/IfEqualizer/Slot/RxFilter.py
RsCmwBase/Implementations/Catalog/Correction/IfEqualizer/Slot/TxFilter.py
RsCmwBase/Implementations/Catalog/Correction/IfEqualizer/Slot/__init__.py
RsCmwBase/Implementations/Cmwd/State.py
RsCmwBase/Implementations/Cmwd/__init__.py
RsCmwBase/Implementations/Configure/Adjustment.py
RsCmwBase/Implementations/Configure/Cmwd.py
RsCmwBase/Implementations/Configure/Ipcr.py
RsCmwBase/Implementations/Configure/__init__.py
RsCmwBase/Implementations/Configure/Correction/__init__.py
RsCmwBase/Implementations/Configure/Correction/IfEqualizer/__init__.py
RsCmwBase/Implementations/Configure/Correction/IfEqualizer/Slot/__init__.py
RsCmwBase/Implementations/Configure/Correction/IfEqualizer/Slot/RxFilter/Select.py
RsCmwBase-4.0.110.dist-info/METADATA
RsCmwBase-4.0.110.dist-info/WHEEL
RsCmwBase-4.0.110.dist-info/top_level.txt
RsCmwBase-4.0.110.dist-info/RECORD
